ssh_mitm_plugins/__entrypoints__.py
ssh_mitm_plugins/__init__.py
ssh_mitm_plugins/ssh/__init__.py
ssh_mitm_plugins/ssh/injectorshell.py
ssh_mitm_plugins/ssh/putty_dos.py
ssh_mitm_plugins/ssh/scriptedshell.py
ssh_mitm_plugins/ssh/stealthshell.py
ssh_mitm_plugins/tunnel/__init__.py
ssh_mitm_plugins/tunnel/injectclienttunnel.py
ssh_mitm_plugins-0.6.1.dist-info/LICENSE
ssh_mitm_plugins-0.6.1.dist-info/METADATA
ssh_mitm_plugins-0.6.1.dist-info/WHEEL
ssh_mitm_plugins-0.6.1.dist-info/entry_points.txt
ssh_mitm_plugins-0.6.1.dist-info/top_level.txt
ssh_mitm_plugins-0.6.1.dist-info/RECORD
