Metadata-Version: 2.1
Name: ssh-mitm-plugins
Version: 0.6.1
Summary: advanced features for ssh-mitm server
Home-page: https://github.com/ssh-mitm/ssh-mitm-plugins
Author: Simon Böhm
Author-email: support@ssh-mitm.at
License: UNKNOWN
Project-URL: Documentation, https://ssh-mitm-plugins.readthedocs.io
Project-URL: Source, https://github.com/ssh-mitm/ssh-mitm-plugins
Project-URL: Tracker, https://github.com/ssh-mitm/ssh-mitm-plugins/issues
Keywords: ssh proxy mitm network security audit plugins features advanced
Platform: UNKNOWN
Classifier: Programming Language :: Python :: 3
Classifier: Programming Language :: Python :: 3.6
Classifier: Programming Language :: Python :: 3.7
Classifier: Programming Language :: Python :: 3.8
Classifier: License :: OSI Approved :: GNU Lesser General Public License v3 (LGPLv3)
Classifier: Topic :: System :: Networking
Classifier: Development Status :: 4 - Beta
Requires-Python: >= 3.6
License-File: LICENSE
Requires-Dist: ssh-mitm (>=1.0.0)
